netdispatch/AGraph.py
netdispatch/__init__.py
netdispatch-0.0.9.dist-info/METADATA
netdispatch-0.0.9.dist-info/WHEEL
netdispatch-0.0.9.dist-info/top_level.txt
netdispatch-0.0.9.dist-info/RECORD
